optlnls/__init__.py
optlnls/constants.py
optlnls/crystal.py
optlnls/epics_functions.py
optlnls/fitting.py
optlnls/fzp.py
optlnls/gaussian_schell.py
optlnls/grating.py
optlnls/hybrid.py
optlnls/image.py
optlnls/importing.py
optlnls/math.py
optlnls/mirror.py
optlnls/misc.py
optlnls/plot.py
optlnls/reflec.py
optlnls/shadow.py
optlnls/source.py
optlnls/stitching.py
optlnls/surface.py
optlnls/testing.py
optlnls/wavefront.py
optlnls/hybrid_funcs/__init__.py
optlnls/hybrid_funcs/propagate.py
optlnls/hybrid_funcs/utility.py
optlnls/materials/Au_f1_nist.txt
optlnls/materials/Au_f2_nist.txt
optlnls/materials/Cr_f1_nist.txt
optlnls/materials/Cr_f2_nist.txt
optlnls/materials/Ni_f1_nist.txt
optlnls/materials/Ni_f2_nist.txt
optlnls/materials/Pt_f1_nist.txt
optlnls/materials/Pt_f2_nist.txt
optlnls/materials/Rh_f1_nist.txt
optlnls/materials/Rh_f2_nist.txt
optlnls/materials/Si_f1_nist.txt
optlnls/materials/Si_f2_nist.txt
optlnls/materials/__init__.py
optlnls-0.3.16.dist-info/LICENSE.txt
optlnls-0.3.16.dist-info/METADATA
optlnls-0.3.16.dist-info/WHEEL
optlnls-0.3.16.dist-info/top_level.txt
optlnls-0.3.16.dist-info/RECORD
