Metadata-Version: 2.1
Name: optlnls
Version: 0.3.16
Summary: X-ray optics utilities
Home-page: https://github.com/oasys-lnls-kit/optlnls
Author: Sergio Lordano
Author-email: sergiolordano2@gmail.com
License: UNKNOWN
Platform: UNKNOWN
Classifier: Programming Language :: Python :: 3
Classifier: License :: OSI Approved :: MIT License
Classifier: Operating System :: OS Independent
Requires-Python: >=2.7
License-File: LICENSE.txt
